scholarsort/__init__.py
scholarsort/author.py
scholarsort/impact_factor.py
scholarsort/journal.py
scholarsort/scholarly.py
scholarsort-0.1.0a1.dist-info/licenses/LICENSE
scholarsort-0.1.0a1.dist-info/METADATA
scholarsort-0.1.0a1.dist-info/WHEEL
scholarsort-0.1.0a1.dist-info/top_level.txt
scholarsort-0.1.0a1.dist-info/RECORD
