Metadata-Version: 2.4
Name: scholarsort
Version: 0.1.0a1
Summary: A Python library for scholarly research with impact factor analysis
Home-page: https://github.com/scholarsort-team/scholarsort
Author: ScholarSort Team
Author-email: ScholarSort Team <team@scholarsort.org>
Maintainer-email: ScholarSort Team <team@scholarsort.org>
License-Expression: MIT
Project-URL: Homepage, https://github.com/scholarsort-team/scholarsort
Project-URL: Documentation, https://scholarsort.readthedocs.io/
Project-URL: Repository, https://github.com/scholarsort-team/scholarsort
Project-URL: Bug Tracker, https://github.com/scholarsort-team/scholarsort/issues
Keywords: scholarly,research,impact factor,academic,citations
Classifier: Development Status :: 3 - Alpha
Classifier: Intended Audience :: Science/Research
Classifier: Operating System :: OS Independent
Classifier: Programming Language :: Python :: 3
Classifier: Programming Language :: Python :: 3.8
Classifier: Programming Language :: Python :: 3.9
Classifier: Programming Language :: Python :: 3.10
Classifier: Programming Language :: Python :: 3.11
Classifier: Programming Language :: Python :: 3.12
Classifier: Topic :: Scientific/Engineering
Classifier: Topic :: Software Development :: Libraries :: Python Modules
Requires-Python: >=3.8
License-File: LICENSE
Requires-Dist: requests>=2.25.0
Requires-Dist: beautifulsoup4>=4.9.0
Requires-Dist: lxml>=4.6.0
Requires-Dist: pandas>=1.3.0
Requires-Dist: numpy>=1.20.0
Requires-Dist: aiohttp>=3.8.0
Requires-Dist: asyncio
Requires-Dist: fake-useragent>=0.1.11
Provides-Extra: dev
Requires-Dist: pytest>=6.0; extra == "dev"
Requires-Dist: pytest-asyncio; extra == "dev"
Requires-Dist: black; extra == "dev"
Requires-Dist: flake8; extra == "dev"
Requires-Dist: mypy; extra == "dev"
Requires-Dist: pre-commit; extra == "dev"
Provides-Extra: docs
Requires-Dist: sphinx; extra == "docs"
Requires-Dist: sphinx-rtd-theme; extra == "docs"
Dynamic: author
Dynamic: home-page
Dynamic: license-file
Dynamic: requires-python
